morphops/__init__.py
morphops/_version.py
morphops/io.py
morphops/lmk_util.py
morphops/procrustes.py
morphops/tps.py
morphops/tests/__init__.py
morphops/tests/helpers.py
morphops/tests/test_lmk_util.py
morphops/tests/test_procrustesalgos.py
morphops/tests/test_procrustesbasics.py
morphops/tests/test_tps.py
morphops-0.1.13.dist-info/LICENSE
morphops-0.1.13.dist-info/METADATA
morphops-0.1.13.dist-info/WHEEL
morphops-0.1.13.dist-info/top_level.txt
morphops-0.1.13.dist-info/RECORD
