Metadata-Version: 2.1
Name: morphops
Version: 0.1.13
Summary: Geometric Morphometrics operations in Python
Home-page: https://github.com/vaipatel/morphops
Author: Vaibhav Patel
Author-email: vai.pateln@gmail.com
License: MIT
Platform: UNKNOWN
Classifier: Programming Language :: Python :: 3 :: Only
Classifier: Programming Language :: Python :: 3.5
Classifier: Programming Language :: Python :: 3.6
Classifier: Programming Language :: Python :: 3.7
Classifier: Programming Language :: Python :: 3.8
Classifier: Programming Language :: Python :: 3.9
Classifier: License :: OSI Approved :: MIT License
Classifier: Topic :: Scientific/Engineering
Requires-Python: >=3.5.1
Provides-Extra: tests
Provides-Extra: docs
Provides-Extra: dev
License-File: LICENSE
